schiene/__init__.py
schiene/schiene.py
schiene-0.23.dist-info/METADATA
schiene-0.23.dist-info/RECORD
schiene-0.23.dist-info/WHEEL
schiene-0.23.dist-info/top_level.txt
