Metadata-Version: 1.0
Name: schiene
Version: 0.23
Summary: schiene is a Python library for interacting with Bahn.de
Home-page: https://github.com/kennell/schiene
Author: Kevin Kennell
Author-email: kevin@kennell.de
License: MIT
Keywords: bahn,api
Platform: UNKNOWN
